distoptica/__init__.py
distoptica/version.py
distoptica-0.4.4.dist-info/licenses/LICENSE
distoptica-0.4.4.dist-info/METADATA
distoptica-0.4.4.dist-info/WHEEL
distoptica-0.4.4.dist-info/top_level.txt
distoptica-0.4.4.dist-info/RECORD
